tinybird_mcp_claude/__init__.py
tinybird_mcp_claude/server.py
tinybird_mcp_claude/tb.py
tinybird_mcp_claude-0.1.3.dist-info/METADATA
tinybird_mcp_claude-0.1.3.dist-info/WHEEL
tinybird_mcp_claude-0.1.3.dist-info/entry_points.txt
tinybird_mcp_claude-0.1.3.dist-info/RECORD
