Metadata-Version: 2.3
Name: tinybird-mcp-claude
Version: 0.1.3
Summary: A MCP server for Claude to interact with a Tinybird Workspace
Project-URL: homepage, https://github.com/tinybirdco/tinybird_mcp_claude
Author-email: alrocar <alrocar@tinybird.co>
Requires-Python: >=3.10
Requires-Dist: httpx>=0.27.2
Requires-Dist: mcp>=1.0.0
Requires-Dist: python-dotenv>=1.0.1
